<?xml version="1.0" encoding="UTF-8" ?>
<dataStructure name="sid.org.tmforum.tip.cbe.loc.local.AbsoluteLocalLocation">
  <container>true</container>
  <description><![CDATA[<p></p>                <p>This entity  is  optional</p>]]></description>
  <extends>dstruct_tip.internal.entity.EntityBase</extends>
  <guid>{cb2f6197-b621-4eea-940a-29c48fb49c29}</guid>
  <label>AbsoluteLocalLocation</label>
  <metaVersion>4</metaVersion>
  <xmlMap type="xmap">
    <includeXsiType>true</includeXsiType>
  </xmlMap>
  <childList>
    <child name="x" type="dstruct">
      <datatype>true</datatype>
      <description><![CDATA[
        <p></p>                                <p>This element is generated from an attribute.</p>                                <p>This attribute  is  optional</p>
      ]]></description>
      <element>dtype_com.conceptwave.system.String</element>
      <guid>{fa74e768-7d9c-47a1-906b-21ff96e9a4f3}</guid>
      <label>x</label>
    </child>
    <child name="y" type="dstruct">
      <datatype>true</datatype>
      <description><![CDATA[
        <p></p>                                <p>This element is generated from an attribute.</p>                                <p>This attribute  is  optional</p>
      ]]></description>
      <element>dtype_com.conceptwave.system.String</element>
      <guid>{8968521c-eb23-4f3d-abce-e5db1b199955}</guid>
      <label>y</label>
    </child>
    <child name="z" type="dstruct">
      <datatype>true</datatype>
      <description><![CDATA[
        <p></p>                                <p>This element is generated from an attribute.</p>                                <p>This attribute  is  optional</p>
      ]]></description>
      <element>dtype_com.conceptwave.system.String</element>
      <guid>{4109065d-d4ad-4151-8b85-b6fbacbf1982}</guid>
      <label>z</label>
    </child>
    <child name="localContinuativeCoordSystem" type="dstruct">
      <description><![CDATA[
        <p></p>                                <p>This element is generated from an association end.</p>                                <p>This association end  has  multiplicity 0..1</p>                                <p>This association end  has  aggregation none</p>                                <p>This association end  is  navigable</p>                                <p>This association end  is  an end of association AbsoluteLocationDefinedUsing</p>                                <p>This association end  is  optional</p>
      ]]></description>
      <element>dstruct_sid.org.tmforum.tip.cbe.loc.local.LocalContinuativeCoordSystem</element>
      <guid>{d5bafe9f-3d64-4c69-8704-de9aa3803497}</guid>
      <label>localContinuativeCoordSystem</label>
    </child>
  </childList>
  <UserInterface name="UserInterface" type="tree">
    <defaultFolderImage>undefined</defaultFolderImage>
    <defaultLeafImage>undefined</defaultLeafImage>
    <element>dstruct_sid.org.tmforum.tip.cbe.loc.local.AbsoluteLocalLocation</element>
    <extends>tree_com.conceptwave.system.DataStructureUserInterface</extends>
    <tableDoc>doc_com.conceptwave.system.TreeDocument</tableDoc>
    <variableList>
      <variable name="model" type="uivar">
        <label>model</label>
        <valueType>dstruct_sid.org.tmforum.tip.cbe.loc.local.AbsoluteLocalLocation</valueType>
      </variable>
    </variableList>
    <vformList>
      <vform name="Forms" type="frmui">
        <extends>tree_com.conceptwave.system.DataStructureUserInterface/frmui_Forms</extends>
      </vform>
    </vformList>
  </UserInterface>
</dataStructure>