<?xml version="1.0" encoding="UTF-8" ?>
<dataStructure name="OCSProvision.accountManagement.v1.types.QueryCustomerResponseType">
  <container>true</container>
  <guid>{7de7a1a8-01ea-4845-a83b-968a09d16272}</guid>
  <label>QueryCustomerResponseType</label>
  <metaVersion>4</metaVersion>
  <xmlMap type="xmap">
    <includeXsiType>true</includeXsiType>
  </xmlMap>
  <childList>
    <child name="result" type="dstruct">
      <element>dstruct_OCSProvision.v1.types.result</element>
      <guid>{14ae8363-e61d-497e-83f2-4980255a4d81}</guid>
      <label>result</label>
      <mandatory>true</mandatory>
    </child>
    <child name="subscriberDetailedInfo" type="dstruct">
      <element>dstruct_OCSProvision.v1.types.subscriberDetailedInfo</element>
      <guid>{020b0ca0-6f1c-4954-bb9a-abb328d3c3d0}</guid>
      <label>subscriberDetailedInfo</label>
      <mandatory>true</mandatory>
    </child>
    <child name="walletInfoList" type="dstruct">
      <element>dstruct_OCSProvision.v1.types.walletInfoList</element>
      <guid>{ce0e341f-6a19-4b6b-b741-9c779ab17cd4}</guid>
      <label>walletInfoList</label>
    </child>
    <child name="boltonDetailedInfoList" type="dstruct">
      <element>dstruct_OCSProvision.v1.types.boltonDetailedInfoList</element>
      <guid>{0f997db1-8e88-4c49-ac15-14dec9a5999a}</guid>
      <label>boltonDetailedInfoList</label>
    </child>
    <child name="uccBasicInfoList" type="dstruct">
      <element>dstruct_OCSProvision.v1.types.uccBasicInfoList</element>
      <guid>{68d7a0c6-5673-4491-94d3-4f311726477e}</guid>
      <label>uccBasicInfoList</label>
    </child>
    <child name="extension" type="dstruct">
      <array>true</array>
      <element>dstruct_common.v2.ExtensionType</element>
      <guid>{c9e2afd1-6440-4796-8271-99de5b366e7b}</guid>
      <label>extension</label>
      <maxInstance>-1</maxInstance>
    </child>
  </childList>
  <UserInterface name="UserInterface" type="tree">
    <defaultFolderImage>undefined</defaultFolderImage>
    <defaultLeafImage>undefined</defaultLeafImage>
    <element>dstruct_OCSProvision.accountManagement.v1.types.QueryCustomerResponseType</element>
    <extends>tree_com.conceptwave.system.DataStructureUserInterface</extends>
    <tableDoc>doc_com.conceptwave.system.TreeDocument</tableDoc>
    <variableList>
      <variable name="model" type="uivar">
        <label>model</label>
        <valueType>dstruct_OCSProvision.accountManagement.v1.types.QueryCustomerResponseType</valueType>
      </variable>
    </variableList>
    <vformList>
      <vform name="Forms" type="frmui">
        <extends>tree_com.conceptwave.system.DataStructureUserInterface/frmui_Forms</extends>
      </vform>
    </vformList>
  </UserInterface>
</dataStructure>