<?xml version="1.0" encoding="UTF-8" ?>
<dataStructure name="sid.org.tmforum.tip.customer.billing.AppliedCustomerBillingRate">
  <abstract>true</abstract>
  <container>true</container>
  <description><![CDATA[
    <p>A charge or a credit assigned to the customer's account in the course or for the purpose of the billing process. Subclasses further define these elements.</p>                <p>This entity  is  abstract</p>                <p>This entity  is  optional</p>
  ]]></description>
  <extends>dstruct_tip.internal.entity.EntityBase</extends>
  <guid>{7dd68e46-7a5b-46e7-b64c-e26a8b2f6e9b}</guid>
  <label>AppliedCustomerBillingRate</label>
  <metaVersion>4</metaVersion>
  <xmlMap type="xmap">
    <includeXsiType>true</includeXsiType>
  </xmlMap>
  <childList>
    <child name="date" type="dstruct">
      <datatype>true</datatype>
      <description><![CDATA[
        <p>A date of creation.</p>                                <p>This element is generated from an attribute.</p>                                <p>This attribute  is  optional</p>
      ]]></description>
      <element>dtype_com.conceptwave.system.Date</element>
      <guid>{9a3f5b34-c643-4790-a925-d3f7bf06ba9f}</guid>
      <label>date</label>
    </child>
    <child name="quantity" type="dstruct">
      <description><![CDATA[
        <p>A unit (for example, US Dollars) and number of the applied rate.</p>                                <p>This element is generated from an attribute.</p>                                <p>This attribute  is  optional</p>
      ]]></description>
      <element>dstruct_tip.cbe.base.Money</element>
      <guid>{0b0a60d3-1ffd-4fca-ab2c-0a85fb75c9ec}</guid>
      <label>quantity</label>
    </child>
    <child name="description" type="dstruct">
      <datatype>true</datatype>
      <description><![CDATA[
        <p>A textual description.</p>                                <p>This element is generated from an attribute.</p>                                <p>This attribute  is  optional</p>
      ]]></description>
      <element>dtype_com.conceptwave.system.String</element>
      <guid>{89129650-abb7-4730-95d7-50cf02fef913}</guid>
      <label>description</label>
    </child>
    <child name="paymentItem" type="dstruct">
      <description><![CDATA[
        <p></p>                                <p>This element is generated from an association end.</p>                                <p>This association end  has  multiplicity 0..1</p>                                <p>This association end  has  aggregation none</p>                                <p>This association end  is  navigable</p>                                <p>This association end  is  unique</p>                                <p>This association end  is  an end of association IitemPaidForAppliedCustomerBilltingRate</p>                                <p>This association end  is  optional</p>
      ]]></description>
      <element>dstruct_sid.org.tmforum.tip.customer.bcoll.pay.PaymentItem</element>
      <guid>{9fa70f8c-3e45-4440-92aa-ce1300ea27b2}</guid>
      <label>paymentItem</label>
    </child>
    <child name="customerBill" type="dstruct">
      <description><![CDATA[
        <p></p>                                <p>This element is generated from an association end.</p>                                <p>This association end  has  multiplicity 0..1</p>                                <p>This association end  has  aggregation shared</p>                                <p>This association end  is  navigable</p>                                <p>This association end  is  an end of association CustomerBillPresentsACBR</p>                                <p>This association end  is  optional</p>
      ]]></description>
      <element>dstruct_sid.org.tmforum.tip.customer.bill.CustomerBill</element>
      <guid>{c92c157d-2412-4f0f-827e-07ff015e0b27}</guid>
      <label>customerBill</label>
    </child>
    <child name="characteristicValue" type="dstruct">
      <description><![CDATA[
        <p></p>                                <p>This element is generated from an association end.</p>                                <p>This association end  has  multiplicity *</p>                                <p>This association end  has  aggregation none</p>                                <p>This association end  is  navigable</p>                                <p>This association end  is  unique</p>                                <p>This association end  is  an end of association ACBRDescribedBy</p>                                <p>This association end  is  optional</p>
      ]]></description>
      <element>dstruct_sid.org.tmforum.tip.cbe.root.ch.ArrayOfCharacteristicValue</element>
      <guid>{9e9b5de7-2b0f-40da-973a-98555a75a52e}</guid>
      <label>characteristicValue</label>
    </child>
    <child name="appliedCustomerBillingRateSpec" type="dstruct">
      <description><![CDATA[
        <p></p>                                <p>This element is generated from an association end.</p>                                <p>This association end  has  multiplicity 0..1</p>                                <p>This association end  has  aggregation none</p>                                <p>This association end  is  navigable</p>                                <p>This association end  is  unique</p>                                <p>This association end  is  an end of association ACBRSpecDescribes</p>                                <p>This association end  is  optional</p>
      ]]></description>
      <element>dstruct_sid.org.tmforum.tip.customer.billing.AppliedCustomerBillingRateSpec</element>
      <guid>{41a9ad93-6f22-4c20-8971-7cbe93a1ecea}</guid>
      <label>appliedCustomerBillingRateSpec</label>
    </child>
    <child name="appliedCustomerBillingProductAlteration" type="dstruct">
      <description><![CDATA[
        <p></p>                                <p>This element is generated from an association end.</p>                                <p>This association end  has  multiplicity *</p>                                <p>This association end  has  aggregation none</p>                                <p>This association end  is  navigable</p>                                <p>This association end  is  an end of association AppliedCreditRefersTo</p>                                <p>This association end  is  optional</p>
      ]]></description>
      <element>dstruct_sid.org.tmforum.tip.customer.billing.ArrayOfAppliedCustomerBillingProductAlteration</element>
      <guid>{25e66e86-99df-4015-b939-f939cd9f355c}</guid>
      <label>appliedCustomerBillingProductAlteration</label>
    </child>
    <child name="appliedCustomerBillingTaxRate" type="dstruct">
      <description><![CDATA[
        <p></p>                                <p>This element is generated from an association end.</p>                                <p>This association end  has  multiplicity *</p>                                <p>This association end  has  aggregation none</p>                                <p>This association end  is  navigable</p>                                <p>This association end  is  an end of association AppliedTaxRateRefersTo</p>                                <p>This association end  is  optional</p>
      ]]></description>
      <element>dstruct_sid.org.tmforum.tip.customer.billing.ArrayOfAppliedCustomerBillingTaxRate</element>
      <guid>{8eda3e9c-d9c2-488f-b4c1-1b3e80eacb5c}</guid>
      <label>appliedCustomerBillingTaxRate</label>
    </child>
    <child name="compositeAppliedCustomerBillingRate" type="dstruct">
      <description><![CDATA[
        <p></p>                                <p>This element is generated from an association end.</p>                                <p>This association end  has  multiplicity *</p>                                <p>This association end  has  aggregation shared</p>                                <p>This association end  is  navigable</p>                                <p>This association end  is  an end of association CompositeAppliedRateComprisedOf</p>                                <p>This association end  is  optional</p>
      ]]></description>
      <element>dstruct_sid.org.tmforum.tip.customer.billing.ArrayOfCompositeAppliedCustomerBillingRate</element>
      <guid>{23a382af-c0b3-4c25-a1db-085cf9d880b7}</guid>
      <label>compositeAppliedCustomerBillingRate</label>
    </child>
  </childList>
  <UserInterface name="UserInterface" type="tree">
    <defaultFolderImage>undefined</defaultFolderImage>
    <defaultLeafImage>undefined</defaultLeafImage>
    <element>dstruct_sid.org.tmforum.tip.customer.billing.AppliedCustomerBillingRate</element>
    <extends>tree_com.conceptwave.system.DataStructureUserInterface</extends>
    <tableDoc>doc_com.conceptwave.system.TreeDocument</tableDoc>
    <variableList>
      <variable name="model" type="uivar">
        <label>model</label>
        <valueType>dstruct_sid.org.tmforum.tip.customer.billing.AppliedCustomerBillingRate</valueType>
      </variable>
    </variableList>
    <vformList>
      <vform name="Forms" type="frmui">
        <extends>tree_com.conceptwave.system.DataStructureUserInterface/frmui_Forms</extends>
      </vform>
    </vformList>
  </UserInterface>
</dataStructure>