<?xml version="1.0" encoding="UTF-8" ?>
<dataStructure name="sid.org.tmforum.tip.cbe.party.IndividualName">
  <container>true</container>
  <description><![CDATA[
    <p>A word, term, or phrase by which an individual is known and distinguished from other individuals.A name is an informal way of identifying an object [Fowler]This entity allows for international naming variations. An IndividualName is a type of PartyName.</p>                <p>This entity  is  optional</p>
  ]]></description>
  <extends>dstruct_tip.internal.entity.EntityBase</extends>
  <guid>{7c9780d0-a4db-459d-b736-90f5404376d7}</guid>
  <label>IndividualName</label>
  <metaVersion>4</metaVersion>
  <xmlMap type="xmap">
    <includeXsiType>true</includeXsiType>
  </xmlMap>
  <childList>
    <child name="formattedName" type="dstruct">
      <datatype>true</datatype>
      <description><![CDATA[
        <p>Contains, in one string, a fully formatted name with all of its pieces in their proper place. This includes all of the necessary punctuation. This de-normalized form of the name cannot be easily parsed.</p>                                <p>This element is generated from an attribute.</p>                                <p>This attribute  is  optional</p>
      ]]></description>
      <element>dtype_com.conceptwave.system.String</element>
      <guid>{691bf907-e0d3-4c9b-8b2d-a6bab46d061d}</guid>
      <label>formattedName</label>
    </child>
    <child name="legalName" type="dstruct">
      <datatype>true</datatype>
      <description><![CDATA[
        <p>Contains, in one string, a fully formatted name with all of its pieces in their proper place. This includes all of the necessary punctuation</p>                                <p>This element is generated from an attribute.</p>                                <p>This attribute  is  optional</p>
      ]]></description>
      <element>dtype_com.conceptwave.system.String</element>
      <guid>{0e301f63-ca93-4480-8dfe-a0886c44e613}</guid>
      <label>legalName</label>
    </child>
    <child name="formOfAddress" type="dstruct">
      <datatype>true</datatype>
      <description><![CDATA[
        <p>Contains the Salutation,e.g. Mr., Mrs., Hon., Dr.,Major, etc</p>                                <p>This element is generated from an attribute.</p>                                <p>This attribute  is  optional</p>
      ]]></description>
      <element>dtype_com.conceptwave.system.String</element>
      <guid>{25358142-6932-4c53-9fb1-48b9e033201a}</guid>
      <label>formOfAddress</label>
    </child>
    <child name="generation" type="dstruct">
      <datatype>true</datatype>
      <description><![CDATA[
        <p>e.g. Sr., Jr., III (the third), etc.</p>                                <p>This element is generated from an attribute.</p>                                <p>This attribute  is  optional</p>
      ]]></description>
      <element>dtype_com.conceptwave.system.String</element>
      <guid>{87b85bef-d216-4204-a696-5cb75d56bc5a}</guid>
      <label>generation</label>
    </child>
    <child name="givenNames" type="dstruct">
      <datatype>true</datatype>
      <description><![CDATA[
        <p></p>                                <p>This element is generated from an attribute.</p>                                <p>This attribute  is  optional</p>
      ]]></description>
      <element>dtype_com.conceptwave.system.String</element>
      <guid>{52752191-a16b-4cfb-bb5d-3d8cfa7b60a1}</guid>
      <label>givenNames</label>
    </child>
    <child name="preferredGivenName" type="dstruct">
      <datatype>true</datatype>
      <description><![CDATA[
        <p>Contains the chosen name by which the person prefers to be addressed. Note: This name may be a name other than a given name, such as a nickname</p>                                <p>This element is generated from an attribute.</p>                                <p>This attribute  is  optional</p>
      ]]></description>
      <element>dtype_com.conceptwave.system.String</element>
      <guid>{8ceadb5a-1f56-4484-95b6-37b380b119f3}</guid>
      <label>preferredGivenName</label>
    </child>
    <child name="middleNames" type="dstruct">
      <datatype>true</datatype>
      <description><![CDATA[
        <p>Middle name(s) or initial(s)</p>                                <p>This element is generated from an attribute.</p>                                <p>This attribute  is  optional</p>
      ]]></description>
      <element>dtype_com.conceptwave.system.String</element>
      <guid>{c2cd96fa-32dc-46d4-b349-7c8ca0f36d47}</guid>
      <label>middleNames</label>
    </child>
    <child name="familyNamePrefix" type="dstruct">
      <datatype>true</datatype>
      <description><![CDATA[
        <p></p>                                <p>This element is generated from an attribute.</p>                                <p>This attribute  is  optional</p>
      ]]></description>
      <element>dtype_com.conceptwave.system.String</element>
      <guid>{d4ba062b-bd06-4342-a06b-2743d86eb5f0}</guid>
      <label>familyNamePrefix</label>
    </child>
    <child name="familyNames" type="dstruct">
      <datatype>true</datatype>
      <description><![CDATA[
        <p>Contains the non-chosen or inherited name. Also known as a person's last name in the Western context.</p>                                <p>This element is generated from an attribute.</p>                                <p>This attribute  is  optional</p>
      ]]></description>
      <element>dtype_com.conceptwave.system.String</element>
      <guid>{58ae5859-aa2c-4463-ac19-a101fe933e4f}</guid>
      <label>familyNames</label>
    </child>
    <child name="familyGeneration" type="dstruct">
      <datatype>true</datatype>
      <description><![CDATA[
        <p>i.e. Sr, Jr</p>                                <p>This element is generated from an attribute.</p>                                <p>This attribute  is  optional</p>
      ]]></description>
      <element>dtype_com.conceptwave.system.String</element>
      <guid>{bc878b87-34ac-44b6-a7f2-608f4240d31c}</guid>
      <label>familyGeneration</label>
    </child>
    <child name="qualifications" type="dstruct">
      <datatype>true</datatype>
      <description><![CDATA[
        <p>Contains the letters used to describe academic or other type qualifications held by a person and/or the distinctions conferred upon them. e.g. PhD, MD, CPA, MCSD, etc</p>                                <p>This element is generated from an attribute.</p>                                <p>This attribute  is  optional</p>
      ]]></description>
      <element>dtype_com.conceptwave.system.String</element>
      <guid>{ee688fe8-6ed3-4191-b2de-05c4f5293f9e}</guid>
      <label>qualifications</label>
    </child>
    <child name="aristocraticTitle" type="dstruct">
      <datatype>true</datatype>
      <description><![CDATA[
        <p>e.g. Baron, Graf, Earl, etc."</p>                                <p>This element is generated from an attribute.</p>                                <p>This attribute  is  optional</p>
      ]]></description>
      <element>dtype_com.conceptwave.system.String</element>
      <guid>{d0d08c59-b9fc-44c0-9413-304807987388}</guid>
      <label>aristocraticTitle</label>
    </child>
    <child name="individual" type="dstruct">
      <description><![CDATA[
        <p></p>                                <p>This element is generated from an association end.</p>                                <p>This association end  has  multiplicity 0..1</p>                                <p>This association end  has  aggregation shared</p>                                <p>This association end  is  navigable</p>                                <p>This association end  is  an end of association IndividualIsNamedUsing</p>                                <p>This association end  is  optional</p>
      ]]></description>
      <element>dstruct_sid.org.tmforum.tip.cbe.party.Individual</element>
      <guid>{578dfdcc-3934-4ee9-88fb-708ff3d693f7}</guid>
      <label>individual</label>
    </child>
  </childList>
  <UserInterface name="UserInterface" type="tree">
    <defaultFolderImage>undefined</defaultFolderImage>
    <defaultLeafImage>undefined</defaultLeafImage>
    <element>dstruct_sid.org.tmforum.tip.cbe.party.IndividualName</element>
    <extends>tree_com.conceptwave.system.DataStructureUserInterface</extends>
    <tableDoc>doc_com.conceptwave.system.TreeDocument</tableDoc>
    <variableList>
      <variable name="model" type="uivar">
        <label>model</label>
        <valueType>dstruct_sid.org.tmforum.tip.cbe.party.IndividualName</valueType>
      </variable>
    </variableList>
    <vformList>
      <vform name="Forms" type="frmui">
        <extends>tree_com.conceptwave.system.DataStructureUserInterface/frmui_Forms</extends>
      </vform>
    </vformList>
  </UserInterface>
</dataStructure>