<?xml version="1.0" encoding="UTF-8" ?><dataStructure name="sid.org.tmforum.tip.cbe.project.scrum.ArrayOfSCRUM_Team">  <container>true</container>  <guid>{3373454c-57d2-434e-bdff-1d16c3502ca2}</guid>  <label>ArrayOfSCRUM_Team</label>  <metaVersion>4</metaVersion>  <xmlMap type="xmap">    <includeXsiType>true</includeXsiType>  </xmlMap>  <childList>    <child name="item" type="dstruct">      <array>true</array>      <element>dstruct_sid.org.tmforum.tip.cbe.project.scrum.SCRUM_Team</element>      <guid>{966a2954-c494-4814-9590-3813c59607f4}</guid>      <label>item</label>      <maxInstance>-1</maxInstance>    </child>  </childList>  <UserInterface name="UserInterface" type="tree">    <defaultFolderImage>undefined</defaultFolderImage>    <defaultLeafImage>undefined</defaultLeafImage>    <element>dstruct_sid.org.tmforum.tip.cbe.project.scrum.ArrayOfSCRUM_Team</element>    <extends>tree_com.conceptwave.system.DataStructureUserInterface</extends>    <tableDoc>doc_com.conceptwave.system.TreeDocument</tableDoc>    <variableList>      <variable name="model" type="uivar">        <label>model</label>        <valueType>dstruct_sid.org.tmforum.tip.cbe.project.scrum.ArrayOfSCRUM_Team</valueType>      </variable>    </variableList>    <vformList>      <vform name="Forms" type="frmui">        <extends>tree_com.conceptwave.system.DataStructureUserInterface/frmui_Forms</extends>      </vform>    </vformList>  </UserInterface></dataStructure>