<?xml version="1.0" encoding="UTF-8" ?><dataStructure name="sid.org.tmforum.tip.cbe.project.scrum.ArrayOfSCRUM_ScrumMaster">  <container>true</container>  <guid>{b5bed982-ac13-4791-818b-e8104a256ce4}</guid>  <label>ArrayOfSCRUM_ScrumMaster</label>  <metaVersion>4</metaVersion>  <xmlMap type="xmap">    <includeXsiType>true</includeXsiType>  </xmlMap>  <childList>    <child name="item" type="dstruct">      <array>true</array>      <element>dstruct_sid.org.tmforum.tip.cbe.project.scrum.SCRUM_ScrumMaster</element>      <guid>{38b8f588-f23e-4ee6-8c06-fb7748cfd14f}</guid>      <label>item</label>      <maxInstance>-1</maxInstance>    </child>  </childList>  <UserInterface name="UserInterface" type="tree">    <defaultFolderImage>undefined</defaultFolderImage>    <defaultLeafImage>undefined</defaultLeafImage>    <element>dstruct_sid.org.tmforum.tip.cbe.project.scrum.ArrayOfSCRUM_ScrumMaster</element>    <extends>tree_com.conceptwave.system.DataStructureUserInterface</extends>    <tableDoc>doc_com.conceptwave.system.TreeDocument</tableDoc>    <variableList>      <variable name="model" type="uivar">        <label>model</label>        <valueType>dstruct_sid.org.tmforum.tip.cbe.project.scrum.ArrayOfSCRUM_ScrumMaster</valueType>      </variable>    </variableList>    <vformList>      <vform name="Forms" type="frmui">        <extends>tree_com.conceptwave.system.DataStructureUserInterface/frmui_Forms</extends>      </vform>    </vformList>  </UserInterface></dataStructure>