<?xml version="1.0" encoding="UTF-8" ?><dataStructure name="sid.org.tmforum.tip.cbe.project.act.ArrayOfSimpleActivitySpec">  <container>true</container>  <guid>{62d76742-732d-4e1e-b18f-3585d3571450}</guid>  <label>ArrayOfSimpleActivitySpec</label>  <metaVersion>4</metaVersion>  <xmlMap type="xmap">    <includeXsiType>true</includeXsiType>  </xmlMap>  <childList>    <child name="item" type="dstruct">      <array>true</array>      <element>dstruct_sid.org.tmforum.tip.cbe.project.act.SimpleActivitySpec</element>      <guid>{9a9f50be-bbb8-4202-b00b-01aff252169e}</guid>      <label>item</label>      <maxInstance>-1</maxInstance>    </child>  </childList>  <UserInterface name="UserInterface" type="tree">    <defaultFolderImage>undefined</defaultFolderImage>    <defaultLeafImage>undefined</defaultLeafImage>    <element>dstruct_sid.org.tmforum.tip.cbe.project.act.ArrayOfSimpleActivitySpec</element>    <extends>tree_com.conceptwave.system.DataStructureUserInterface</extends>    <tableDoc>doc_com.conceptwave.system.TreeDocument</tableDoc>    <variableList>      <variable name="model" type="uivar">        <label>model</label>        <valueType>dstruct_sid.org.tmforum.tip.cbe.project.act.ArrayOfSimpleActivitySpec</valueType>      </variable>    </variableList>    <vformList>      <vform name="Forms" type="frmui">        <extends>tree_com.conceptwave.system.DataStructureUserInterface/frmui_Forms</extends>      </vform>    </vformList>  </UserInterface></dataStructure>