<?xml version="1.0" encoding="UTF-8" ?>
<dataStructure name="cm_spoc.data.Duo">
  <container>true</container>
  <extends>dstruct_cm_spoc.data.OCSProductSpecification</extends>
  <group>Lists</group>
  <guid>{964d7bb7-ddd3-4249-abc6-cc4f9c1bb827}</guid>
  <jsonMap type="jmap"/>
  <label>Duo</label>
  <metaVersion>4</metaVersion>
  <childList>
    <child name="ApplyShortDialing" type="dstruct">
      <datatype>true</datatype>
      <element>dtype_cm_spoc.data.OCSBooleanAttribute</element>
      <guid>{61fdf006-d91c-4a4a-ab04-b0adf6802602}</guid>
      <jsonMap type="jmap"/>
      <label>ApplyShortDialing</label>
    </child>
    <child name="DuoDialing" type="dstruct">
      <datatype>true</datatype>
      <element>dtype_cm_spoc.data.OCSString28Attribute</element>
      <guid>{c47fabea-c8dd-4ba6-a219-7c1fd3032a2b}</guid>
      <jsonMap type="jmap"/>
      <label>DuoDialing</label>
    </child>
    <child name="DuoLength" type="dstruct">
      <datatype>true</datatype>
      <element>dtype_cm_spoc.data.OCSNumber2Attribute</element>
      <guid>{dcbb94ba-e87c-4f73-9f7b-ee6fadb0f75f}</guid>
      <jsonMap type="jmap"/>
      <label>DuoLength</label>
    </child>
    <child name="CheckLength" type="dstruct">
      <datatype>true</datatype>
      <element>dtype_cm_spoc.data.OCSBooleanAttribute</element>
      <guid>{b540e759-bec2-4d4c-9c90-9c6527ccb105}</guid>
      <jsonMap type="jmap"/>
      <label>CheckLength</label>
    </child>
    <child name="CheckTon" type="dstruct">
      <datatype>true</datatype>
      <element>dtype_cm_spoc.data.OCSBooleanAttribute</element>
      <guid>{1d7cd8ac-43b9-4b0d-a7f9-def32883778a}</guid>
      <jsonMap type="jmap"/>
      <label>CheckTon</label>
    </child>
    <child name="DuoNumberTON" type="dstruct">
      <datatype>true</datatype>
      <element>dtype_cwt_pcdd.catalogCode</element>
      <guid>{2be6ea09-c058-4468-8788-383b5d20c214}</guid>
      <jsonMap type="jmap"/>
      <label>DuoNumberTON</label>
    </child>
    <child name="DuoNumberTonEnum" type="dstruct">
      <datatype>true</datatype>
      <element>dtype_cm_spoc.data.DuoNumberTonEnum</element>
      <guid>{0764499b-6a60-4613-a461-5102e48c8cce}</guid>
      <jsonMap type="jmap"/>
      <label>DuoNumberTonEnum</label>
    </child>
  </childList>
  <UserInterface name="UserInterface" type="tree">
    <defaultFolderImage>undefined</defaultFolderImage>
    <defaultLeafImage>undefined</defaultLeafImage>
    <element>dstruct_cm_spoc.data.Duo</element>
    <extends>tree_com.conceptwave.system.DataStructureUserInterface</extends>
    <tableDoc>doc_com.conceptwave.system.TreeDocument</tableDoc>
    <variableList>
      <variable name="model" type="uivar">
        <label>model</label>
        <valueType>dstruct_cm_spoc.data.Duo</valueType>
      </variable>
    </variableList>
    <vformList>
      <vform name="Forms" type="frmui">
        <extends>tree_com.conceptwave.system.DataStructureUserInterface/frmui_Forms</extends>
      </vform>
    </vformList>
  </UserInterface>
</dataStructure>