<?xml version="1.0" encoding="UTF-8" ?>
<dataStructure name="cm_spoc.data.ServiceTariffPlanGroup">
  <container>true</container>
  <extends>dstruct_cm_spoc.data.OCSProductOffering</extends>
  <group>ServiceTariffPlan</group>
  <guid>{7cbf8a84-cc41-4a4b-a423-a2adb306fcbb}</guid>
  <jsonMap type="jmap"/>
  <label>ServiceTariffPlanGroup</label>
  <metaVersion>4</metaVersion>
  <childList>
    <child name="ServiceTariffPlanGroupID" type="dstruct">
      <datatype>true</datatype>
      <element>dtype_cm_spoc.data.OCSNumber4Attribute</element>
      <guid>{298663fd-ceee-4050-806f-137e198d551d}</guid>
      <jsonMap type="jmap"/>
      <label>ServiceTariffPlanGroupID</label>
      <mandatory>true</mandatory>
    </child>
    <child name="ServiceTariffPlanGroupDescriptio" type="dstruct">
      <datatype>true</datatype>
      <element>dtype_cm_spoc.data.OCSString200Attribute</element>
      <guid>{6878c40a-cea3-4f8d-b5d2-6f005bbae738}</guid>
      <jsonMap type="jmap"/>
      <label>ServiceTariffPlanGroupDescriptio</label>
      <mandatory>true</mandatory>
    </child>
    <child name="DefaultBoltOnTypeListDS" type="dstruct">
      <element>dstruct_cm_spoc.data.DefaultBoltOnTypeList</element>
      <guid>{e14056e6-a507-4490-87b1-5ceefe1b3903}</guid>
      <jsonMap type="jmap"/>
      <label>DefaultBoltOnTypeListDS</label>
    </child>
    <child name="STPGServiceTPArr" type="dstruct">
      <datatype>true</datatype>
      <element>dtype_cwt_pcdd.catalogCode</element>
      <guid>{55484c0f-ff8c-4135-b277-2623be3e4443}</guid>
      <jsonMap type="jmap"/>
      <label>STPGServiceTPArr</label>
    </child>
    <child name="STPGServiceTPArrDS" type="dstruct">
      <element>dstruct_cm_spoc.data.STPGServiceTPArr</element>
      <guid>{6fc7adf5-4d21-4958-b8e6-5e696891280a}</guid>
      <jsonMap type="jmap"/>
      <label>STPGServiceTPArrDS</label>
    </child>
    <child name="DefaultBoltOnTypeList" type="dstruct">
      <datatype>true</datatype>
      <element>dtype_cwt_pcdd.catalogCode</element>
      <guid>{6c439041-d62c-4307-907c-2053cc45a7b0}</guid>
      <jsonMap type="jmap"/>
      <label>DefaultBoltOnTypeList</label>
    </child>
  </childList>
  <UserInterface name="UserInterface" type="tree">
    <defaultFolderImage>undefined</defaultFolderImage>
    <defaultLeafImage>undefined</defaultLeafImage>
    <element>dstruct_cm_spoc.data.ServiceTariffPlanGroup</element>
    <extends>tree_com.conceptwave.system.DataStructureUserInterface</extends>
    <tableDoc>doc_com.conceptwave.system.TreeDocument</tableDoc>
    <variableList>
      <variable name="model" type="uivar">
        <label>model</label>
        <valueType>dstruct_cm_spoc.data.ServiceTariffPlanGroup</valueType>
      </variable>
    </variableList>
    <vformList>
      <vform name="Forms" type="frmui">
        <extends>tree_com.conceptwave.system.DataStructureUserInterface/frmui_Forms</extends>
      </vform>
    </vformList>
  </UserInterface>
</dataStructure>