<?xml version="1.0" encoding="UTF-8" ?>
<script name="cm_spoc.onSettingThresholdSetSpecification">
  <group>ui_scripts.UsageControl.Triggers</group>
  <label>onSettingThresholdSetSpecification</label>
  <metaVersion>4</metaVersion>
  <parameterList>
    <parameter name="ui" type="rifp">
      <type>ui_com.conceptwave.system.UserInterface</type>
    </parameter>
  </parameterList>
  <script><![CDATA[
    //
    ui.model.UsageControlThresholdSetSpeDS.UCThSetSpecifArrDS.ListDS[0].Cyclic = ui.Cyclic1;
    ui.model.UsageControlThresholdSetSpeDS.UCThSetSpecifArrDS.ListDS[0].UsageThresholdAmount = ui.UsageThresholdAmount1;

    ui.model.UsageControlThresholdSetSpeDS.UCThSetSpecifArrDS.ListDS[1].Cyclic = ui.Cyclic2;
    ui.model.UsageControlThresholdSetSpeDS.UCThSetSpecifArrDS.ListDS[1].UsageThresholdAmount = ui.UsageThresholdAmount2;

    ui.model.UsageControlThresholdSetSpeDS.UCThSetSpecifArrDS.ListDS[2].Cyclic = ui.Cyclic3;
    ui.model.UsageControlThresholdSetSpeDS.UCThSetSpecifArrDS.ListDS[2].UsageThresholdAmount = ui.UsageThresholdAmount3;

    ui.model.UsageControlThresholdSetSpeDS.UCThSetSpecifArrDS.ListDS[3].Cyclic = ui.Cyclic4;
    ui.model.UsageControlThresholdSetSpeDS.UCThSetSpecifArrDS.ListDS[3].UsageThresholdAmount = ui.UsageThresholdAmount4;

    ui.model.UsageControlThresholdSetSpeDS.UCThSetSpecifArrDS.ListDS[4].Cyclic = ui.Cyclic5;
    ui.model.UsageControlThresholdSetSpeDS.UCThSetSpecifArrDS.ListDS[4].UsageThresholdAmount = ui.UsageThresholdAmount5;

    return;
  ]]></script>
</script>