<?xml version="1.0" encoding="UTF-8" ?>
<dataStructure name="sid.org.tmforum.tip.enterprise.risk.ra.kpi.RevenueAssuranceKPIConsequence">
  <container>true</container>
  <description><![CDATA[
    <p>An action taken if a RevenueAssuranceObjective is not met for a RevenueAssuranceKPI.</p>                <p>This entity  is  optional</p>
  ]]></description>
  <extends>dstruct_tip.internal.entity.EntityBase</extends>
  <guid>{1c7f14fa-d89b-4a08-9097-5b63804b1d8b}</guid>
  <label>RevenueAssuranceKPIConsequence</label>
  <metaVersion>4</metaVersion>
  <xmlMap type="xmap">
    <includeXsiType>true</includeXsiType>
  </xmlMap>
  <childList>
    <child name="revenueAssuranceTroubleTicketSpec" type="dstruct">
      <description><![CDATA[
        <p></p>                                <p>This element is generated from an association end.</p>                                <p>This association end  has  multiplicity *</p>                                <p>This association end  has  aggregation none</p>                                <p>This association end  is  navigable</p>                                <p>This association end  is  an end of association RevenueAssuranceKPIConsequenceInfluences</p>                                <p>This association end  is  optional</p>
      ]]></description>
      <element>dstruct_sid.org.tmforum.tip.enterprise.risk.ra.tt.ArrayOfRevenueAssuranceTroubleTicketSpec</element>
      <guid>{47387720-2c9c-4603-a832-9eb75b11f50a}</guid>
      <label>revenueAssuranceTroubleTicketSpec</label>
    </child>
  </childList>
  <UserInterface name="UserInterface" type="tree">
    <defaultFolderImage>undefined</defaultFolderImage>
    <defaultLeafImage>undefined</defaultLeafImage>
    <element>dstruct_sid.org.tmforum.tip.enterprise.risk.ra.kpi.RevenueAssuranceKPIConsequence</element>
    <extends>tree_com.conceptwave.system.DataStructureUserInterface</extends>
    <tableDoc>doc_com.conceptwave.system.TreeDocument</tableDoc>
    <variableList>
      <variable name="model" type="uivar">
        <label>model</label>
        <valueType>dstruct_sid.org.tmforum.tip.enterprise.risk.ra.kpi.RevenueAssuranceKPIConsequence</valueType>
      </variable>
    </variableList>
    <vformList>
      <vform name="Forms" type="frmui">
        <extends>tree_com.conceptwave.system.DataStructureUserInterface/frmui_Forms</extends>
      </vform>
    </vformList>
  </UserInterface>
</dataStructure>