<?xml version="1.0" encoding="UTF-8" ?>
<interface name="cm_aaca.opgeRereadingInt">
  <group>opgeRereading.externalServices</group>
  <guid>{0ae4b9d3-a040-46cb-96d0-5d80eac909d8}</guid>
  <label>OPGE ReReading Interfaz</label>
  <metaVersion>4</metaVersion>
  <operationList>
    <operation name="invokeTuxedo" type="oper">
      <input>dstruct_cm_aaca.in_invokeTuxedo</input>
      <label>Invoke ReReading</label>
      <output>dstruct_cm_aaca.out_invokeTuxedo</output>
      <type>Request-Response</type>
    </operation>
    <operation name="addMemoryZoneToPendingQueue" type="oper">
      <input>dstruct_cm_aaca.in_addMemoryZoneToPendingQueue</input>
      <label>Add NumMessage Memory Zone</label>
      <type>Request-Response</type>
    </operation>
  </operationList>
  <revision>4</revision>
</interface>