<?xml version="1.0" encoding="UTF-8" ?>
<dataStructure name="OCSProvision.listAndTribeManagement.v1.types.deleteListMemberResponse">
  <container>true</container>
  <extends>dstruct_OCSProvision.listAndTribeManagement.v1.types.DeleteListMemberResponseType</extends>
  <guid>{a42135df-6c56-4e6f-9b94-20b46e4adcba}</guid>
  <label>deleteListMemberResponse</label>
  <metaVersion>4</metaVersion>
  <xmlMap type="xmap">
    <isElement>true</isElement>
  </xmlMap>
  <UserInterface name="UserInterface" type="tree">
    <defaultFolderImage>undefined</defaultFolderImage>
    <defaultLeafImage>undefined</defaultLeafImage>
    <element>dstruct_OCSProvision.listAndTribeManagement.v1.types.deleteListMemberResponse</element>
    <extends>tree_com.conceptwave.system.DataStructureUserInterface</extends>
    <tableDoc>doc_com.conceptwave.system.TreeDocument</tableDoc>
    <variableList>
      <variable name="model" type="uivar">
        <label>model</label>
        <valueType>dstruct_OCSProvision.listAndTribeManagement.v1.types.deleteListMemberResponse</valueType>
      </variable>
    </variableList>
    <vformList>
      <vform name="Forms" type="frmui">
        <extends>tree_com.conceptwave.system.DataStructureUserInterface/frmui_Forms</extends>
      </vform>
    </vformList>
  </UserInterface>
</dataStructure>