<?xml version="1.0" encoding="UTF-8" ?><dataStructure name="sid.org.tmforum.tip.resource.spec.catalog.ArrayOfResourceCandidate">  <container>true</container>  <guid>{b8958cd7-f812-4483-a6f3-2abde69096a4}</guid>  <label>ArrayOfResourceCandidate</label>  <metaVersion>4</metaVersion>  <xmlMap type="xmap">    <includeXsiType>true</includeXsiType>  </xmlMap>  <childList>    <child name="item" type="dstruct">      <array>true</array>      <element>dstruct_sid.org.tmforum.tip.resource.spec.catalog.ResourceCandidate</element>      <guid>{15b27c76-91bb-415f-80c0-66284c078cda}</guid>      <label>item</label>      <maxInstance>-1</maxInstance>    </child>  </childList>  <UserInterface name="UserInterface" type="tree">    <defaultFolderImage>undefined</defaultFolderImage>    <defaultLeafImage>undefined</defaultLeafImage>    <element>dstruct_sid.org.tmforum.tip.resource.spec.catalog.ArrayOfResourceCandidate</element>    <extends>tree_com.conceptwave.system.DataStructureUserInterface</extends>    <tableDoc>doc_com.conceptwave.system.TreeDocument</tableDoc>    <variableList>      <variable name="model" type="uivar">        <label>model</label>        <valueType>dstruct_sid.org.tmforum.tip.resource.spec.catalog.ArrayOfResourceCandidate</valueType>      </variable>    </variableList>    <vformList>      <vform name="Forms" type="frmui">        <extends>tree_com.conceptwave.system.DataStructureUserInterface/frmui_Forms</extends>      </vform>    </vformList>  </UserInterface></dataStructure>